CHANGES.txt
MANIFEST.in
README.rst
setup.py
isotoma/__init__.py
isotoma.recipe.cluster.egg-info/PKG-INFO
isotoma.recipe.cluster.egg-info/SOURCES.txt
isotoma.recipe.cluster.egg-info/dependency_links.txt
isotoma.recipe.cluster.egg-info/entry_points.txt
isotoma.recipe.cluster.egg-info/namespace_packages.txt
isotoma.recipe.cluster.egg-info/not-zip-safe
isotoma.recipe.cluster.egg-info/requires.txt
isotoma.recipe.cluster.egg-info/top_level.txt
isotoma/recipe/__init__.py
isotoma/recipe/cluster/__init__.py
isotoma/recipe/cluster/ctl.py
isotoma/recipe/cluster/recipe.py
isotoma/recipe/cluster/tests.py
isotoma/recipe/cluster/testservice.py