Metadata-Version: 1.0
Name: isotoma.recipe.cluster
Version: 0.0.8
Summary: Buildout recipe for generating cluster start/stop scripts.
Home-page: http://pypi.python.org/pypi/isotoma.recipe.cluster
Author: John Carr
Author-email: john.carr@isotoma.com
License: Apache Software License
Keywords: buildout cluster
Platform: UNKNOWN
Classifier: Framework :: Buildout
Classifier: Framework :: Buildout :: Recipe
Classifier: Intended Audience :: System Administrators
Classifier: Operating System :: POSIX
Classifier: License :: OSI Approved :: Apache Software License
